CHANGES
LICENSE
MANIFEST.in
README
setup.py
bin/piscan-setup.sh
piscan/__init__.py
piscan/clearqueue.py
piscan/piconfig.py
piscan/piqueue.py
piscan/pirec.py
piscan.egg-info/PKG-INFO
piscan.egg-info/SOURCES.txt
piscan.egg-info/dependency_links.txt
piscan.egg-info/not-zip-safe
piscan.egg-info/requires.txt
piscan.egg-info/top_level.txt
piscan/data/__init__.py
piscan/data/boto.cfg
piscan/data/piqueue.sh
piscan/data/pirec.sh
piscan/data/piscan.ini
piscan/data/piwi.sh
piscan/frontend/__init__.py
piscan/frontend/piwi.py
piscan/frontend/static/RXWave.gif
piscan/frontend/static/__init__.py
piscan/frontend/static/favicon.ico
piscan/frontend/static/menustyles.css
piscan/frontend/static/old_menustyles.css
piscan/frontend/static/script.js
piscan/frontend/templates/__init__.py
piscan/frontend/templates/index.html