Metadata-Version: 1.0
Name: piscan
Version: 0.2.6
Summary: RXWave.com Uniden DMA Police Scanner agent
Home-page: http://www.rxwave.com
Author: Dave Kolberg
Author-email: dave@netagile.com
License: MIT
Keywords: RXwave Police-scanner Uniden DMA RXWave.com RX-Wave.com radio scanner
Platform: UNKNOWN
